[
  {
    "tweet_id": "1765899672571560044",
    "analysis": {
      "virality_potential": {
        "score": 8,
        "justification": "Discusses ETF potential and historical price comparisons between ETH/BTC - topics likely to generate strong engagement in crypto communities."
      },
      "informative_value": {
        "score": 7,
        "justification": "Provides specific price comparisons and regulatory speculation, though lacks direct sources for ETF claims."
      },
      "sentiment_polarity": {
        "score": 7,
        "justification": "Moderately positive tone advocating Ethereum's potential while criticizing Bitcoin's inflation."
      },
      "duration_of_impact": {
        "score": 7,
        "justification": "ETF discussions and fundamental comparisons between major cryptos remain relevant for weeks/months."
      }
    }
  },
  {
    "tweet_id": "1765835905976164458",
    "analysis": {
      "virality_potential": {
        "score": 6,
        "justification": "Price prediction format common in crypto circles, but lacks unique angle for broader sharing."
      },
      "informative_value": {
        "score": 3,
        "justification": "Makes speculative price claims without supporting data or context."
      },
      "sentiment_polarity": {
        "score": 8,
        "justification": "Very positive tone suggesting investment opportunity."
      },
      "duration_of_impact": {
        "score": 4,
        "justification": "Price-specific claims become outdated quickly as markets fluctuate."
      }
    }
  },
  {
    "tweet_id": "1765815082376740871",
    "analysis": {
      "virality_potential": {
        "score": 7,
        "justification": "Community-specific call-to-action with comparison to SOL's performance could drive engagement."
      },
      "informative_value": {
        "score": 6,
        "justification": "Announces specific event timeline but lacks details about the claim process."
      },
      "sentiment_polarity": {
        "score": 5,
        "justification": "Neutral informational tone with implied urgency."
      },
      "duration_of_impact": {
        "score": 3,
        "justification": "Primarily relevant only until the claim window closes."
      }
    }
  },
  {
    "tweet_id": "1765803384458948784",
    "analysis": {
      "virality_potential": {
        "score": 5,
        "justification": "Engagement bait format (like if...) with crypto theme, limited to niche community."
      },
      "informative_value": {
        "score": 2,
        "justification": "No substantive information beyond meme-style trading regret."
      },
      "sentiment_polarity": {
        "score": 4,
        "justification": "Mildly negative tone about trading mistakes."
      },
      "duration_of_impact": {
        "score": 2,
        "justification": "Meme-style content typically has short lifespan."
      }
    }
  },
  {
    "tweet_id": "1765580934407987317",
    "analysis": {
      "virality_potential": {
        "score": 6,
        "justification": "Relatable analogy about crypto accessibility could resonate in retail investor circles."
      },
      "informative_value": {
        "score": 4,
        "justification": "Presents a user behavior thesis without supporting data."
      },
      "sentiment_polarity": {
        "score": 5,
        "justification": "Neutral analytical tone making platform comparison."
      },
      "duration_of_impact": {
        "score": 6,
        "justification": "Thesis about platform adoption could remain relevant through market cycle."
      }
    }
  },
  {
    "tweet_id": "1765321693503832471",
    "analysis": {
      "virality_potential": {
        "score": 5,
        "justification": "Conference reporting common in crypto but lacks unique angle."
      },
      "informative_value": {
        "score": 5,
        "justification": "Notes conference activity without specific news or insights."
      },
      "sentiment_polarity": {
        "score": 5,
        "justification": "Neutral reportage tone."
      },
      "duration_of_impact": {
        "score": 3,
        "justification": "Conference updates typically fade after event concludes."
      }
    }
  },
  {
    "tweet_id": "1764782662495989951",
    "analysis": {
      "virality_potential": {
        "score": 8,
        "justification": "Major regulatory news about Ethereum ETF likely to spread quickly."
      },
      "informative_value": {
        "score": 8,
        "justification": "Specific regulatory action from SEC with market implications."
      },
      "sentiment_polarity": {
        "score": 2,
        "justification": "Negative tone mocking Ethereum supporters ('dudes')."
      },
      "duration_of_impact": {
        "score": 7,
        "justification": "ETF delays impact medium-term market expectations."
      }
    }
  },
  {
    "tweet_id": "1764778172761923634",
    "analysis": {
      "virality_potential": {
        "score": 9,
        "justification": "Breaking regulatory news from account with large following, high retweet count."
      },
      "informative_value": {
        "score": 9,
        "justification": "Clear statement of significant regulatory action affecting major financial product."
      },
      "sentiment_polarity": {
        "score": 5,
        "justification": "Neutral reporting style despite negative content."
      },
      "duration_of_impact": {
        "score": 8,
        "justification": "ETF decisions have long-term regulatory implications."
      }
    }
  },
  {
    "tweet_id": "1764673182600929551",
    "analysis": {
      "virality_potential": {
        "score": 8,
        "justification": "High-value NFT transaction notable in crypto art community."
      },
      "informative_value": {
        "score": 7,
        "justification": "Specific transaction details with verifiable on-chain data."
      },
      "sentiment_polarity": {
        "score": 5,
        "justification": "Neutral reporting of sale facts."
      },
      "duration_of_impact": {
        "score": 6,
        "justification": "Notable NFT sales remain reference points in market history."
      }
    }
  },
  {
    "tweet_id": "1764619361250075093",
    "analysis": {
      "virality_potential": {
        "score": 7,
        "justification": "Platform rivalry narrative drives engagement in crypto communities."
      },
      "informative_value": {
        "score": 6,
        "justification": "Reports specific metric comparison but lacks source/timestamp context."
      },
      "sentiment_polarity": {
        "score": 7,
        "justification": "Positive tone celebrating Solana's performance."
      },
      "duration_of_impact": {
        "score": 4,
        "justification": "Daily volume metrics quickly superseded by new data."
      }
    }
  }
]